fisheyewarping/__init__.py
fisheyewarping/cli.py
fisheyewarping/fisheyewarping.py
FisheyeWarping-1.0.1.dist-info/LICENSE
FisheyeWarping-1.0.1.dist-info/METADATA
FisheyeWarping-1.0.1.dist-info/WHEEL
FisheyeWarping-1.0.1.dist-info/entry_points.txt
FisheyeWarping-1.0.1.dist-info/top_level.txt
FisheyeWarping-1.0.1.dist-info/RECORD
