Metadata-Version: 2.1
Name: FisheyeWarping
Version: 1.0.1
Summary: Dewarp top-down fisheye image to panorama and rewarp panorama to fisheye image.
Home-page: https://github.com/NatLee/fisheye-warping
Author: Nat Lee
Author-email: natlee.work@gmail.com
Project-URL: Documentation, https://github.com/NatLee/fisheye-warping
Project-URL: Bug Reports, https://github.com/NatLee/fisheye-warping/issues
Project-URL: Source Code, https://github.com/NatLee/fisheye-warping
Keywords: dewarp,rewarp,panorama,fisheye,mesh,cli
Classifier: Development Status :: 5 - Production/Stable
Classifier: Intended Audience :: Developers
Classifier: Topic :: Software Development :: Build Tools
Classifier: Programming Language :: Python :: 3
Classifier: Programming Language :: Python :: 3.6
Classifier: Programming Language :: Python :: 3.7
Classifier: Programming Language :: Python :: 3.8
Classifier: Programming Language :: Python :: 3.9
Classifier: Programming Language :: Python :: 3.10
Classifier: Programming Language :: Python :: 3.11
Classifier: Programming Language :: Python :: 3 :: Only
Classifier: License :: OSI Approved :: MIT License
Classifier: Operating System :: OS Independent
Requires-Python: >=3.6
License-File: LICENSE
Requires-Dist: opencv-python
Requires-Dist: numpy
Requires-Dist: tqdm
Provides-Extra: dev
Requires-Dist: check-manifest ; extra == 'dev'
